mimufs/__init__.py
mimufs/analysis.py
mimufs/mimufs.py
mimufs/processing.py
mimufs/visualization.py
mimufs-0.1.1.dist-info/LICENSE
mimufs-0.1.1.dist-info/METADATA
mimufs-0.1.1.dist-info/WHEEL
mimufs-0.1.1.dist-info/top_level.txt
mimufs-0.1.1.dist-info/RECORD
