Metadata-Version: 2.1
Name: mimufs
Version: 0.1.1
Summary: Mim@uf and BI-CSP Library for Portuguese Primary Care
Home-page: https://github.com/DiogoCarapito/mimufs
Author: Diogo Carapito
Author-email: diogo.carapito@gmail.com
License: Apache License 2.0
Project-URL: Bug Reports, https://github.com/DiogoCarapito/mimufs/issues
Project-URL: Source, https://github.com/DiogoCarapito/mimufs
Keywords: business intelligence,primary care,data science,medicine
Classifier: Development Status :: 2 - Pre-Alpha
Classifier: License :: OSI Approved :: Apache Software License
Classifier: Intended Audience :: Developers
Classifier: Intended Audience :: Healthcare Industry
Classifier: Natural Language :: Portuguese
Classifier: Operating System :: OS Independent
Classifier: Programming Language :: Python :: 3
Classifier: Topic :: Scientific/Engineering :: Information Analysis
Classifier: Topic :: Scientific/Engineering :: Medical Science Apps.
Classifier: Topic :: Scientific/Engineering :: Visualization
Classifier: Topic :: Software Development :: Libraries :: Python Modules
Classifier: Topic :: Utilities
Requires-Python: >=3.7,<3.12
License-File: LICENSE
Requires-Dist: pandas >=2.1.3
Requires-Dist: numpy >=1.26.2
Requires-Dist: matplotlib >=3.8.2
